setup.py
gabd/Binomialdistribution.py
gabd/Gaussiandistribution.py
gabd/Generaldistribution.py
gabd/__init__.py
gabd.egg-info/PKG-INFO
gabd.egg-info/SOURCES.txt
gabd.egg-info/dependency_links.txt
gabd.egg-info/not-zip-safe
gabd.egg-info/top_level.txt