Metadata-Version: 1.0
Name: gabd
Version: 1.7
Summary: Gaussian and Binomial distributions
Home-page: UNKNOWN
Author: Harshit Sachdeva
Author-email: harshitsachdeva98@gmail.com
License: UNKNOWN
Platform: UNKNOWN
